chameleon/__init__.py
chameleon/base/__init__.py
chameleon/base/power_module.py
chameleon/base/utils.py
chameleon/base/blocks/__init__.py
chameleon/base/blocks/conv_block.py
chameleon/base/blocks/mamba_block.py
chameleon/base/blocks/vit_block.py
chameleon/base/components/__init__.py
chameleon/base/components/activation.py
chameleon/base/components/dropout.py
chameleon/base/components/loss.py
chameleon/base/components/norm.py
chameleon/base/components/pooling.py
chameleon/base/layers/__init__.py
chameleon/base/layers/aspp.py
chameleon/base/layers/grl.py
chameleon/base/layers/selayer.py
chameleon/base/layers/vae.py
chameleon/base/layers/weighted_sum.py
chameleon/base/ops/__init__.py
chameleon/base/ops/positional_encoding.py
chameleon/base/optim/__init__.py
chameleon/base/optim/polynomial_lr_warmup.py
chameleon/base/optim/warm_up.py
chameleon/metrics/__init__.py
chameleon/metrics/normalized_levenshtein_similarity.py
chameleon/modules/__init__.py
chameleon/modules/backbones/__init__.py
chameleon/modules/backbones/gpunet.py
chameleon/modules/backbones/timm.py
chameleon/modules/necks/__init__.py
chameleon/modules/necks/bifpn.py
chameleon/modules/necks/fpn.py
chameleon/modules/necks/pafpn.py
chameleon/registry/__init__.py
chameleon/registry/registry.py
chameleon/registry/root.py
chameleon/tools/__init__.py
chameleon/tools/calflops/__init__.py
chameleon/tools/calflops/calculate_pipline.py
chameleon/tools/calflops/flops_counter.py
chameleon/tools/calflops/pytorch_ops.py
chameleon/tools/calflops/utils.py
chameleon_docsaid-0.3.1.dist-info/LICENSE
chameleon_docsaid-0.3.1.dist-info/METADATA
chameleon_docsaid-0.3.1.dist-info/WHEEL
chameleon_docsaid-0.3.1.dist-info/top_level.txt
chameleon_docsaid-0.3.1.dist-info/RECORD
