Metadata-Version: 2.1
Name: chameleon-docsaid
Version: 0.3.1
Summary: Torch based deep learning library.
Home-page: https://github.com/DocsaidLab/Chameleon.git
License: Apache License 2.0
Classifier: Development Status :: 5 - Production/Stable
Classifier: License :: OSI Approved :: Apache Software License
Classifier: Intended Audience :: Developers
Classifier: Intended Audience :: Science/Research
Classifier: Operating System :: OS Independent
Classifier: Programming Language :: Python :: 3.10
Classifier: Programming Language :: Python :: 3.11
Classifier: Programming Language :: Python :: 3.12
Classifier: Topic :: Software Development :: Libraries
Classifier: Topic :: Software Development :: Libraries :: Python Modules
License-File: LICENSE
Requires-Dist: rich
Requires-Dist: timm>=0.5.4
Requires-Dist: torch>=1.13
Requires-Dist: torchvision
Requires-Dist: torchmetrics
